lytest/__init__.py
lytest/command_line.py
lytest/containers.py
lytest/kdb_xor.py
lytest/phidl_oas.py
lytest/utest_buds.py
lytest-0.1.1.dist-info/LICENSE
lytest-0.1.1.dist-info/METADATA
lytest-0.1.1.dist-info/WHEEL
lytest-0.1.1.dist-info/entry_points.txt
lytest-0.1.1.dist-info/top_level.txt
lytest-0.1.1.dist-info/RECORD
