Metadata-Version: 2.1
Name: lytest
Version: 0.1.1
Summary: Regression testing for klayout, phidl, and KiCAD
Home-page: https://github.com/atait/lytest/
Author: Alex Tait, Adam McCaughan, Sonia Buckley, Jeff Chiles, Jeff Shainline, Rich Mirin, Sae Woo Nam
Author-email: atait@ieee.org
License: MIT
License-File: LICENSE
Requires-Dist: pytest
